<APIProxy revision="1" name="MP-DataAPI-v1">
    <DisplayName></DisplayName>
    <Description></Description>
    <CreatedAt>1716907716524</CreatedAt>
    <LastModifiedAt>1716907716524</LastModifiedAt>
    <BasePaths>/v1/data</BasePaths>
    <Policies>
        <Policy>AM-RemoveKey</Policy>
        <Policy>CORS-SetCors</Policy>
        <Policy>EV-ExtractName</Policy>
        <Policy>JS-RunPostTarget-Script</Policy>
        <Policy>JS-RunPreTarget-Script</Policy>
        <Policy>KVM-GetVariables</Policy>
        <Policy>VA-VerifyKey</Policy>
    </Policies>
    <ProxyEndpoints>
        <ProxyEndpoint>default</ProxyEndpoint>
    </ProxyEndpoints>
    <Resources>
        <Resource>jsc://bigquery_functions.js</Resource>
        <Resource>jsc://bigquery_posttarget.js</Resource>
        <Resource>jsc://bigquery_pretarget.js</Resource>
    </Resources>
    <TargetEndpoints>
        <TargetEndpoint>default</TargetEndpoint>
    </TargetEndpoints>
</APIProxy>